{
  "description": "家庭点菜微信小程序项目配置",
  "miniprogramRoot": "miniprogram/",
  "cloudfunctionRoot": "cloudfunctions/",
  "packOptions": {
    "ignore": [
      {
        "value": "node_modules",
        "type": "folder"
      }
    ],
    "include": []
  },
  "setting": {
    "urlCheck": false,
    "es6": true,
    "enhance": true,
    "postcss": true,
    "preloadBackgroundData": false,
    "minified": true,
    "newFeature": true,
    "coverView": true,
    "nodeModules": false,
    "autoAudits": false,
    "showShadowRootInWxmlPanel": true,
    "scopeDataCheck": false,
    "uglifyFileName": false,
    "checkInvalidKey": true,
    "checkSiteMap": true,
    "uploadWithSourceMap": true,
    "compileHotReLoad": false,
    "babelSetting": {
      "ignore": [],
      "disablePlugins": [],
      "outputPath": ""
    },
    "cloud": true,
    "compileWorklet": false,
    "packNpmManually": false,
    "packNpmRelationList": [],
    "minifyWXSS": true,
    "minifyWXML": true,
    "localPlugins": false,
    "disableUseStrict": false,
    "useCompilerPlugins": false,
    "condition": false,
    "swc": false,
    "disableSWC": true
  },
  "compileType": "miniprogram",
  "libVersion": "3.3.5",
  "appid": "wx55d032bf719fa612",
  "projectname": "family-order",
  "condition": {},
  "simulatorPluginLibVersion": {},
  "editorSetting": {}
}